{
  "annotations": {
    "list": [
      {
        "builtIn": 1,
        "datasource": "-- Grafana --",
        "enable": true,
        "hide": true,
        "iconColor": "rgba(0, 211, 255, 1)",
        "name": "Annotations & Alerts",
        "target": {
          "limit": 100,
          "matchAny": false,
          "tags": [],
          "type": "dashboard"
        },
        "type": "dashboard"
      }
    ]
  },
  "editable": true,
  "fiscalYearStartMonth": 0,
  "graphTooltip": 0,
  "id": 6,
  "iteration": 1695808205600,
  "links": [],
  "liveNow": false,
  "panels": [
    {
      "datasource": {
        "type": "grafana-clickhouse-datasource",
        "uid": "PDEE91DDB90597936"
      },
      "gridPos": {
        "h": 22,
        "w": 10,
        "x": 0,
        "y": 0
      },
      "id": 4,
      "options": {
        "color": "yellow",
        "groupByPodLabel": false,
        "layerFour": true
      },
      "targets": [
        {
          "datasource": {
            "type": "grafana-clickhouse-datasource",
            "uid": "PDEE91DDB90597936"
          },
          "meta": {
            "builderOptions": {
              "fields": [],
              "limit": 100,
              "mode": "list"
            }
          },
          "queryType": "sql",
          "rawSql": "SELECT sourcePodName, sourcePodLabels, sourcePodNamespace, sourceNodeName, destinationPodName, destinationPodLabels, destinationNodeName, destinationServicePortName, octetDeltaCount FROM flows\nWHERE sourcePodNamespace NOT IN ('kube-system', 'flow-visibility', 'flow-aggregator')\nAND destinationPodNamespace NOT IN ('kube-system', 'flow-visibility', 'flow-aggregator')\nAND ( destinationPodName != '' OR sourcePodName != '' )\nAND octetDeltaCount != 0\nAND httpVals == ''\nAND $__timeFilter(flowEndSeconds)\nORDER BY flowEndSeconds DESC",
          "refId": "A"
        }
      ],
      "title": "Layer 4 Topology",
      "type": "theia-grafana-dependency-plugin"
    },
    {
      "datasource": {
        "type": "grafana-clickhouse-datasource",
        "uid": "PDEE91DDB90597936"
      },
      "description": "The different colors of the lines mean different codes, but are labelled by the content length of the flow.\nGreen: Success",
      "gridPos": {
        "h": 22,
        "w": 10,
        "x": 10,
        "y": 0
      },
      "id": 2,
      "options": {
        "color": "yellow",
        "groupByLabel": false,
        "groupByPodLabel": false,
        "layerFour": false,
        "seriesCountSize": "sm",
        "showSeriesCount": false,
        "text": "Default value of text input option"
      },
      "targets": [
        {
          "datasource": {
            "type": "grafana-clickhouse-datasource",
            "uid": "PDEE91DDB90597936"
          },
          "format": 1,
          "meta": {
            "builderOptions": {
              "fields": [],
              "limit": 100,
              "mode": "list"
            }
          },
          "queryType": "sql",
          "rawSql": "SELECT sourcePodName, sourcePodLabels, sourcePodNamespace, sourceNodeName, sourceIP, sourceTransportPort, destinationPodName, destinationPodLabels, destinationNodeName, destinationServicePortName, destinationIP, destinationTransportPort, octetDeltaCount, httpVals FROM flows\nWHERE sourcePodNamespace NOT IN ('kube-system', 'flow-visibility', 'flow-aggregator')\nAND destinationPodNamespace NOT IN ('kube-system', 'flow-visibility', 'flow-aggregator')\nAND ( destinationPodName != '' OR sourcePodName != '' )\nAND octetDeltaCount != 0\nAND httpVals != ''\nAND $__timeFilter(flowEndSeconds)\nORDER BY flowEndSeconds DESC",
          "refId": "A"
        }
      ],
      "title": "Layer 7 Topology",
      "type": "theia-grafana-dependency-plugin"
    }
  ],
  "refresh": "",
  "schemaVersion": 34,
  "style": "dark",
  "tags": [],
  "templating": {
    "list": [
      {
        "datasource": {
          "type": "grafana-clickhouse-datasource",
          "uid": "PDEE91DDB90597936"
        },
        "filters": [],
        "hide": 0,
        "name": "Filter",
        "skipUrlSync": false,
        "type": "adhoc"
      },
      {
        "hide": 2,
        "name": "clickhouse_adhoc_query",
        "query": "default.flows",
        "skipUrlSync": false,
        "type": "constant"
      }
    ]
  },
  "time": {
    "from": "now-30m",
    "to": "now"
  },
  "timepicker": {},
  "timezone": "",
  "title": "network_topology_dashboard",
  "uid": "yRVDEad4k",
  "version": 3,
  "weekStart": ""
}